import_export_xml/__init__.py
import_export_xml/formats.py
django_import_export_xml-0.2.0.dist-info/LICENSE
django_import_export_xml-0.2.0.dist-info/METADATA
django_import_export_xml-0.2.0.dist-info/WHEEL
django_import_export_xml-0.2.0.dist-info/top_level.txt
django_import_export_xml-0.2.0.dist-info/RECORD
