Metadata-Version: 2.1
Name: django-import-export-xml
Version: 0.2.0
Summary: An XML export format for django-import-export
Author-email: Maykin Media <support@maykinmedia.nl>
License: MIT License
Project-URL: Homepage, https://github.com/maykinmedia/django-import-export-xml
Project-URL: Bug Tracker, https://github.com/maykinmedia/django-import-export-xml/issues
Project-URL: Source Code, https://github.com/maykinmedia/django-import-export-xml
Keywords: TODO
Classifier: Development Status :: 3 - Alpha
Classifier: Framework :: Django
Classifier: Framework :: Django :: 3.2
Classifier: Framework :: Django :: 4.2
Classifier: Intended Audience :: Developers
Classifier: Operating System :: OS Independent
Classifier: Programming Language :: Python :: 3
Classifier: Programming Language :: Python :: 3.9
Classifier: Programming Language :: Python :: 3.10
Classifier: Programming Language :: Python :: 3.11
Classifier: Programming Language :: Python :: 3.12
Classifier: Topic :: Software Development :: Libraries :: Python Modules
Requires-Python: >=3.9
License-File: LICENSE
Requires-Dist: dicttoxml
Requires-Dist: django-import-export
Provides-Extra: coverage
Requires-Dist: pytest-cov ; extra == 'coverage'
Provides-Extra: release
Requires-Dist: bump-my-version ; extra == 'release'
Requires-Dist: twine ; extra == 'release'
Provides-Extra: tests
Requires-Dist: black ; extra == 'tests'
Requires-Dist: flake8 ; extra == 'tests'
Requires-Dist: isort ; extra == 'tests'
Requires-Dist: pytest ; extra == 'tests'
Requires-Dist: pytest-django ; extra == 'tests'
Requires-Dist: tox ; extra == 'tests'
